<annotation verified="no">
  <folder>1D3001 Frames</folder>
  <filename>1D3001P3-011</filename>
  <path>/home/crnovak/Desktop/1D3001 Frames/1D3001P3-011.png</path>
  <source>
    <database>Unknown</database>
  </source>
  <size>
    <width>1280</width>
    <height>720</height>
    <depth>3</depth>
  </size>
  <segmented>0</segmented>
  <object>
    <name>vehicle</name>
    <pose>Unspecified</pose>
    <truncated>0</truncated>
    <difficult>0</difficult>
    <bndbox>
      <xmin>1078</xmin>
      <ymin>204</ymin>
      <xmax>1178</xmax>
      <ymax>327</ymax>
    </bndbox>
  </object>
  <object>
    <name>vehicle</name>
    <pose>Unspecified</pose>
    <truncated>0</truncated>
    <difficult>0</difficult>
    <bndbox>
      <xmin>108</xmin>
      <ymin>152</ymin>
      <xmax>215</xmax>
      <ymax>254</ymax>
    </bndbox>
  </object>
  <object>
    <name>vehicle</name>
    <pose>Unspecified</pose>
    <truncated>0</truncated>
    <difficult>0</difficult>
    <bndbox>
      <xmin>483</xmin>
      <ymin>137</ymin>
      <xmax>625</xmax>
      <ymax>236</ymax>
    </bndbox>
  </object>
  <object>
    <name>vehicle</name>
    <pose>Unspecified</pose>
    <truncated>0</truncated>
    <difficult>0</difficult>
    <bndbox>
      <xmin>646</xmin>
      <ymin>95</ymin>
      <xmax>769</xmax>
      <ymax>170</ymax>
    </bndbox>
  </object>
</annotation>
