<annotation verified="no">
  <folder>1D3001 Frames</folder>
  <filename>1D3001P2-119</filename>
  <path>/home/crnovak/Desktop/1D3001 Frames/1D3001P2-119.png</path>
  <source>
    <database>Unknown</database>
  </source>
  <size>
    <width>1280</width>
    <height>720</height>
    <depth>3</depth>
  </size>
  <segmented>0</segmented>
  <object>
    <name>vehicle</name>
    <pose>Unspecified</pose>
    <truncated>1</truncated>
    <difficult>0</difficult>
    <bndbox>
      <xmin>1154</xmin>
      <ymin>496</ymin>
      <xmax>1280</xmax>
      <ymax>581</ymax>
    </bndbox>
  </object>
</annotation>
